jetson_sx126x/__init__.py
jetson_sx126x/_sx126x.py
jetson_sx126x/pin.py
jetson_sx126x/sx1261.py
jetson_sx126x/sx1262.py
jetson_sx126x/sx1268.py
jetson_sx126x/sx126x.py
jetson_SX126X-1.0.0.dist-info/LICENSE
jetson_SX126X-1.0.0.dist-info/METADATA
jetson_SX126X-1.0.0.dist-info/WHEEL
jetson_SX126X-1.0.0.dist-info/top_level.txt
jetson_SX126X-1.0.0.dist-info/RECORD
