Metadata-Version: 2.1
Name: jetson-SX126X
Version: 1.0.0
Summary: Semtech SX126X LoRa driver for Jetson TX2
Home-page: https://github.com/MacRover/jetson-SX126X
Author: McMaster Mars Rover
Author-email: marsatmac@gmail.com
Project-URL: Bug Tracker, https://github.com/MacRover/jetson-SX126X/issues
Project-URL: MMRT Website, https://www.marsatmac.ca/
Classifier: Programming Language :: Python :: 3
Classifier: License :: OSI Approved :: MIT License
Classifier: Operating System :: POSIX :: Linux
Requires-Python: >=3.6
License-File: LICENSE
Requires-Dist: Jetson.GPIO (>=2.0.18)
Requires-Dist: python-periphery (>=2.3.0)
